Workbook

Sheet README - Assumptions
A1: NorthPeak Distribution Co. - Sales Performance Analysis
A2: Portfolio dataset: FY2025 sales, generated with realistic, formula-linked business logic.
A4: Business Scenario
A5: • | B5: NorthPeak Distribution Co. is a mid-market B2B/B2C distributor of technology and office solutions operating across four US regions, selling through Online, Retail Partner, and Direct Sales channels to Consumer, SMB, and Enterprise customers.
A7: Scope
A8: • | B8: Sales_Data contains 1,200 orders covering all 12 months of 2025, with unique Order IDs formatted ORD-2025-00001 through ORD-2025-01200.
A9: • | B9: Products contains 20 SKUs across 4 categories (Electronics, Accessories, Office Equipment, Software), each with a Standard Price used as the pricing basis.
A10: • | B10: Monthly_Targets contains 12 rows (Jan-Dec 2025); Sales is a live formula that sums actual order-level Sales from Sales_Data for that month, so it updates automatically if the underlying data changes. Sales Target is a manually set planning figure for comparison.
A12: Pricing & Discount Logic
A13: • | B13: Unit Price = Product Standard Price adjusted by small order-level variance (+/-4%) and a channel effect (Online 1.00x, Retail Partner 0.97x, Direct Sales 0.98x, reflecting wholesale/negotiated pricing).
A14: • | B14: Discount % varies by Customer Segment: Consumer 0-8%, SMB 5-15%, Enterprise 10-25%, with a small channel adjustment (Direct Sales +2%, Online -1%), reflecting that larger buyers negotiate harder.
A15: • | B15: Units per order scale with segment: Consumer 1-3, SMB 3-10, Enterprise 8-40.
A17: Cost & Profitability Logic
A18: • | B18: Cost is driven by category-specific gross-margin structure, expressed as a cost ratio applied to each order's Sales value (Cost = Sales x Cost Ratio): Software ~20-28% (high-margin, digital), Accessories ~55-62%, Office Equipment ~60-68%, Electronics ~68-74% (thin-margin, hardware-heavy). Each order's ratio includes small realistic variance around these category bases.
A19: • | B19: Profit = Sales - Cost, calculated per order and aggregable across any dimension.
A21: Seasonality
A22: • | B22: Order volume follows a realistic seasonal curve: slow start in Jan-Feb, steady growth through mid-year, a back-to-office/school bump in Aug-Sep, and the strongest volume in Nov-Dec (holiday demand).
A23: • | B23: Monthly Sales Targets were set as a smoothed version of realistic monthly plan figures and intentionally do not perfectly track actuals - some months beat target, some miss it, as in a real business.
A25: Formula Integrity
A26: • | B26: Sales_Data: Sales = Units x Unit Price x (1 - Discount %); Cost = Sales x order-level Cost Ratio (rounded); Profit = Sales - Cost. All three are live formulas, not hardcoded values.
A27: • | B27: Monthly_Targets: Sales is a SUMPRODUCT formula that filters Sales_Data by year and month and sums the Sales column - it will recalculate automatically if any order in Sales_Data is added, changed, or removed.
A29: Intended Use
A30: • | B30: This workbook is designed to support Excel PivotTable/dashboard analysis, SQL practice (import Sales_Data, Products, Monthly_Targets as relational tables), and Power BI modeling (Sales_Data as fact table, Products and Monthly_Targets as dimension/reference tables).

Sheet Sales_Data
A1: Order ID | B1: Order Date | C1: Region | D1: Category | E1: Product | F1: Customer Segment | G1: Sales Channel | H1: Salesperson | I1: Units | J1: Unit Price | K1: Discount % | L1: Sales | M1: Cost | N1: Profit
A2: ORD-2025-00001 | B2: 45658 | C2: Northeast | D2: Office Equipment | E2: Standing Desk | F2: Enterprise | G2: Direct Sales | H2: Daniel Brooks | I2: 37 | J2: 397.5 | K2: 0.1751 | L2: =I2*J2*(1-K2) -> 12132.217 | M2: =ROUND(L2*0.654,2) -> 7934.47 | N2: =L2-M2 -> 4197.7467
A3: ORD-2025-00002 | B3: 45658 | C3: Southeast | D3: Office Equipment | E3: Laser Printer | F3: Consumer | G3: Retail Partner | H3: Maria Gonzalez | I3: 1 | J3: 240.85 | K3: 0.0813 | L3: =I3*J3*(1-K3) -> 221.26889 | M3: =ROUND(L3*0.6321,2) -> 139.86 | N3: =L3-M3 -> 81.408895
A4: ORD-2025-00003 | B4: 45659 | C4: West | D4: Electronics | E4: Laptop Pro 14 | F4: Consumer | G4: Online | H4: Online Store - West | I4: 1 | J4: 1252.95 | K4: 0.0438 | L4: =I4*J4*(1-K4) -> 1198.0708 | M4: =ROUND(L4*0.7311,2) -> 875.91 | N4: =L4-M4 -> 322.16079
A5: ORD-2025-00004 | B5: 45660 | C5: Northeast | D5: Electronics | E5: Tablet Pro 11 | F5: SMB | G5: Retail Partner | H5: Emily Carter | I5: 6 | J5: 682.31 | K5: 0.1011 | L5: =I5*J5*(1-K5) -> 3679.9708 | M5: =ROUND(L5*0.6849,2) -> 2520.41 | N5: =L5-M5 -> 1159.5608
A6: ORD-2025-00005 | B6: 45660 | C6: Northeast | D6: Office Equipment | E6: All-in-One Printer | F6: Enterprise | G6: Direct Sales | H6: Emily Carter | I6: 39 | J6: 190.56 | K6: 0.1979 | L6: =I6*J6*(1-K6) -> 5961.0789 | M6: =ROUND(L6*0.6661,2) -> 3970.67 | N6: =L6-M6 -> 1990.4089
A7: ORD-2025-00006 | B7: 45662 | C7: West | D7: Electronics | E7: Laptop Pro 14 | F7: Consumer | G7: Retail Partner | H7: Sophia Martinez | I7: 2 | J7: 1231.69 | K7: 0.0412 | L7: =I7*J7*(1-K7) -> 2361.8887 | M7: =ROUND(L7*0.7218,2) -> 1704.81 | N7: =L7-M7 -> 657.07874
A8: ORD-2025-00007 | B8: 45662 | C8: Northeast | D8: Accessories | E8: Mechanical Keyboard | F8: Consumer | G8: Retail Partner | H8: Emily Carter | I8: 3 | J8: 83.98 | K8: 0.0744 | L8: =I8*J8*(1-K8) -> 233.19566 | M8: =ROUND(L8*0.5858,2) -> 136.61 | N8: =L8-M8 -> 96.585664
A9: ORD-2025-00008 | B9: 45663 | C9: West | D9: Software | E9: Productivity Suite License | F9: Consumer | G9: Retail Partner | H9: Rachel Adams | I9: 1 | J9: 146.66 | K9: 0.0427 | L9: =I9*J9*(1-K9) -> 140.39762 | M9: =ROUND(L9*0.2566,2) -> 36.03 | N9: =L9-M9 -> 104.36762
A10: ORD-2025-00009 | B10: 45664 | C10: Southeast | D10: Accessories | E10: Wireless Mouse | F10: Consumer | G10: Online | H10: Online Store - Southeast | I10: 2 | J10: 38.22 | K10: 0.0032 | L10: =I10*J10*(1-K10) -> 76.195392 | M10: =ROUND(L10*0.5766,2) -> 43.93 | N10: =L10-M10 -> 32.265392
A11: ORD-2025-00010 | B11: 45664 | C11: Midwest | D11: Accessories | E11: Wireless Headset | F11: Consumer | G11: Online | H11: Online Store - Midwest | I11: 3 | J11: 97.53 | K11: 0.0296 | L11: =I11*J11*(1-K11) -> 283.92934 | M11: =ROUND(L11*0.5932,2) -> 168.43 | N11: =L11-M11 -> 115.49934
A12: ORD-2025-00011 | B12: 45664 | C12: Midwest | D12: Office Equipment | E12: All-in-One Printer | F12: Consumer | G12: Online | H12: Online Store - Midwest | I12: 1 | J12: 194.33 | K12: 0.0556 | L12: =I12*J12*(1-K12) -> 183.52525 | M12: =ROUND(L12*0.6643,2) -> 121.92 | N12: =L12-M12 -> 61.605252
A13: ORD-2025-00012 | B13: 45665 | C13: West | D13: Electronics | E13: Ultrabook Air 13 | F13: Enterprise | G13: Direct Sales | H13: Sophia Martinez | I13: 25 | J13: 1073.01 | K13: 0.2493 | L13: =I13*J13*(1-K13) -> 20137.715 | M13: =ROUND(L13*0.6898,2) -> 13891 | N13: =L13-M13 -> 6246.7152
A14: ORD-2025-00013 | B14: 45665 | C14: West | D14: Electronics | E14: Laptop Pro 14 | F14: Enterprise | G14: Direct Sales | H14: Kevin O'Brien | I14: 20 | J14: 1295.26 | K14: 0.1531 | L14: =I14*J14*(1-K14) -> 21939.114 | M14: =ROUND(L14*0.704,2) -> 15445.14 | N14: =L14-M14 -> 6493.9739
A15: ORD-2025-00014 | B15: 45665 | C15: Southeast | D15: Office Equipment | E15: Laser Printer | F15: Enterprise | G15: Direct Sales | H15: Maria Gonzalez | I15: 28 | J15: 238.41 | K15: 0.1433 | L15: =I15*J15*(1-K15) -> 5718.8837 | M15: =ROUND(L15*0.6631,2) -> 3792.19 | N15: =L15-M15 -> 1926.6937
A16: ORD-2025-00015 | B16: 45665 | C16: Midwest | D16: Software | E16: Productivity Suite License | F16: Consumer | G16: Online | H16: Online Store - Midwest | I16: 1 | J16: 143.13 | K16: 0.0436 | L16: =I16*J16*(1-K16) -> 136.88953 | M16: =ROUND(L16*0.2135,2) -> 29.23 | N16: =L16-M16 -> 107.65953
A17: ORD-2025-00016 | B17: 45666 | C17: Southeast | D17: Electronics | E17: Business Desktop Tower | F17: SMB | G17: Online | H17: Online Store - Southeast | I17: 10 | J17: 879.04 | K17: 0.0627 | L17: =I17*J17*(1-K17) -> 8239.2419 | M17: =ROUND(L17*0.7076,2) -> 5830.09 | N17: =L17-M17 -> 2409.1519
A18: ORD-2025-00017 | B18: 45666 | C18: West | D18: Electronics | E18: Business Desktop Tower | F18: Consumer | G18: Retail Partner | H18: Sophia Martinez | I18: 3 | J18: 866.7 | K18: 0.0704 | L18: =I18*J18*(1-K18) -> 2417.053 | M18: =ROUND(L18*0.6802,2) -> 1644.08 | N18: =L18-M18 -> 772.97296
A19: ORD-2025-00018 | B19: 45666 | C19: Southeast | D19: Electronics | E19: Business Desktop Tower | F19: Enterprise | G19: Direct Sales | H19: Maria Gonzalez | I19: 27 | J19: 905.1 | K19: 0.1692 | L19: =I19*J19*(1-K19) -> 20302.841 | M19: =ROUND(L19*0.6919,2) -> 14047.54 | N19: =L19-M19 -> 6255.3012
A20: ORD-2025-00019 | B20: 45667 | C20: West | D20: Office Equipment | E20: Paper Shredder | F20: Consumer | G20: Online | H20: Online Store - West | I20: 1 | J20: 125.4 | K20: 0.0326 | L20: =I20*J20*(1-K20) -> 121.31196 | M20: =ROUND(L20*0.6192,2) -> 75.12 | N20: =L20-M20 -> 46.19196
A21: ORD-2025-00020 | B21: 45667 | C21: Northeast | D21: Electronics | E21: Business Desktop Tower | F21: Enterprise | G21: Direct Sales | H21: Emily Carter | I21: 29 | J21: 865.42 | K21: 0.1992 | L21: =I21*J21*(1-K21) -> 20097.822 | M21: =ROUND(L21*0.7264,2) -> 14599.06 | N21: =L21-M21 -> 5498.7617
A22: ORD-2025-00021 | B22: 45667 | C22: West | D22: Office Equipment | E22: All-in-One Printer | F22: Enterprise | G22: Retail Partner | H22: Sophia Martinez | I22: 14 | J22: 186.44 | K22: 0.1189 | L22: =I22*J22*(1-K22) -> 2299.812 | M22: =ROUND(L22*0.6259,2) -> 1439.45 | N22: =L22-M22 -> 860.36198
A23: ORD-2025-00022 | B23: 45667 | C23: Southeast | D23: Software | E23: Productivity Suite License | F23: SMB | G23: Retail Partner | H23: James Whitfield | I23: 5 | J23: 140.97 | K23: 0.0864 | L23: =I23*J23*(1-K23) -> 643.95096 | M23: =ROUND(L23*0.2327,2) -> 149.85 | N23: =L23-M23 -> 494.10096
A24: ORD-2025-00023 | B24: 45668 | C24: Northeast | D24: Electronics | E24: Laptop Pro 14 | F24: SMB | G24: Retail Partner | H24: Daniel Brooks | I24: 5 | J24: 1276.04 | K24: 0.127 | L24: =I24*J24*(1-K24) -> 5569.9146 | M24: =ROUND(L24*0.7198,2) -> 4009.22 | N24: =L24-M24 -> 1560.6946
A25: ORD-2025-00024 | B25: 45669 | C25: West | D25: Accessories | E25: Laptop Sleeve 14-inch | F25: Consumer | G25: Retail Partner | H25: Rachel Adams | I25: 1 | J25: 27.26 | K25: 0.0056 | L25: =I25*J25*(1-K25) -> 27.107344 | M25: =ROUND(L25*0.5607,2) -> 15.2 | N25: =L25-M25 -> 11.907344
A26: ORD-2025-00025 | B26: 45669 | C26: Southeast | D26: Accessories | E26: Mechanical Keyboard | F26: Enterprise | G26: Direct Sales | H26: Maria Gonzalez | I26: 13 | J26: 84.33 | K26: 0.1931 | L26: =I26*J26*(1-K26) -> 884.5964 | M26: =ROUND(L26*0.5542,2) -> 490.24 | N26: =L26-M26 -> 394.3564
A27: ORD-2025-00026 | B27: 45669 | C27: West | D27: Office Equipment | E27: Laser Printer | F27: Consumer | G27: Online | H27: Online Store - West | I27: 1 | J27: 251.17 | K27: 0.0221 | L27: =I27*J27*(1-K27) -> 245.61914 | M27: =ROUND(L27*0.6537,2) -> 160.56 | N27: =L27-M27 -> 85.059143
A28: ORD-2025-00027 | B28: 45669 | C28: West | D28: Accessories | E28: Wireless Mouse | F28: Enterprise | G28: Direct Sales | H28: Rachel Adams | I28: 8 | J28: 38.52 | K28: 0.2415 | L28: =I28*J28*(1-K28) -> 233.73936 | M28: =ROUND(L28*0.5567,2) -> 130.12 | N28: =L28-M28 -> 103.61936
A29: ORD-2025-00028 | B29: 45670 | C29: Midwest | D29: Electronics | E29: Ultrabook Air 13 | F29: Enterprise | G29: Online | H29: Online Store - Midwest | I29: 8 | J29: 1114.85 | K29: 0.101 | L29: =I29*J29*(1-K29) -> 8018.0012 | M29: =ROUND(L29*0.7331,2) -> 5878 | N29: =L29-M29 -> 2140.0012
A30: ORD-2025-00029 | B30: 45670 | C30: Northeast | D30: Office Equipment | E30: Paper Shredder | F30: SMB | G30: Direct Sales | H30: Daniel Brooks | I30: 10 | J30: 124.25 | K30: 0.0829 | L30: =I30*J30*(1-K30) -> 1139.4968 | M30: =ROUND(L30*0.6538,2) -> 745 | N30: =L30-M30 -> 394.49675
A31: ORD-2025-00030 | B31: 45671 | C31: West | D31: Electronics | E31: 27-inch 4K Monitor | F31: Consumer | G31: Online | H31: Online Store - West | I31: 1 | J31: 456.12 | K31: 0.0352 | L31: =I31*J31*(1-K31) -> 440.06458 | M31: =ROUND(L31*0.6893,2) -> 303.34 | N31: =L31-M31 -> 136.72458
A32: ORD-2025-00031 | B32: 45671 | C32: Northeast | D32: Software | E32: Antivirus Security License | F32: Consumer | G32: Online | H32: Online Store - Northeast | I32: 1 | J32: 59.29 | K32: 0.0251 | L32: =I32*J32*(1-K32) -> 57.801821 | M32: =ROUND(L32*0.2521,2) -> 14.57 | N32: =L32-M32 -> 43.231821
A33: ORD-2025-00032 | B33: 45672 | C33: Midwest | D33: Office Equipment | E33: Standing Desk | F33: SMB | G33: Direct Sales | H33: Robert Chen | I33: 9 | J33: 398.16 | K33: 0.1534 | L33: =I33*J33*(1-K33) -> 3033.7403 | M33: =ROUND(L33*0.6166,2) -> 1870.6 | N33: =L33-M33 -> 1163.1403
A34: ORD-2025-00033 | B34: 45672 | C34: Southeast | D34: Office Equipment | E34: Paper Shredder | F34: SMB | G34: Online | H34: Online Store - Southeast | I34: 9 | J34: 126.44 | K34: 0.0592 | L34: =I34*J34*(1-K34) -> 1070.5928 | M34: =ROUND(L34*0.6112,2) -> 654.35 | N34: =L34-M34 -> 416.24277
A35: ORD-2025-00034 | B35: 45672 | C35: West | D35: Software | E35: Accounting Software License | F35: Consumer | G35: Online | H35: Online Store - West | I35: 1 | J35: 255 | K35: 0.0466 | L35: =I35*J35*(1-K35) -> 243.117 | M35: =ROUND(L35*0.2693,2) -> 65.47 | N35: =L35-M35 -> 177.647
A36: ORD-2025-00035 | B36: 45675 | C36: Northeast | D36: Office Equipment | E36: Laser Printer | F36: Enterprise | G36: Online | H36: Online Store - Northeast | I36: 10 | J36: 254.06 | K36: 0.0972 | L36: =I36*J36*(1-K36) -> 2293.6537 | M36: =ROUND(L36*0.622,2) -> 1426.65 | N36: =L36-M36 -> 867.00368
A37: ORD-2025-00036 | B37: 45675 | C37: West | D37: Accessories | E37: Wireless Mouse | F37: Enterprise | G37: Direct Sales | H37: Kevin O'Brien | I37: 31 | J37: 38.03 | K37: 0.1972 | L37: =I37*J37*(1-K37) -> 946.445 | M37: =ROUND(L37*0.5573,2) -> 527.45 | N37: =L37-M37 -> 418.995
A38: ORD-2025-00037 | B38: 45675 | C38: Northeast | D38: Software | E38: Productivity Suite License | F38: SMB | G38: Online | H38: Online Store - Northeast | I38: 8 | J38: 149.92 | K38: 0.0574 | L38: =I38*J38*(1-K38) -> 1130.5167 | M38: =ROUND(L38*0.2127,2) -> 240.46 | N38: =L38-M38 -> 890.05674
A39: ORD-2025-00038 | B39: 45676 | C39: Midwest | D39: Accessories | E39: Laptop Sleeve 14-inch | F39: Consumer | G39: Retail Partner | H39: Robert Chen | I39: 2 | J39: 27.41 | K39: 0.0261 | L39: =I39*J39*(1-K39) -> 53.389198 | M39: =ROUND(L39*0.5696,2) -> 30.41 | N39: =L39-M39 -> 22.979198
A40: ORD-2025-00039 | B40: 45676 | C40: Southeast | D40: Software | E40: Project Management License | F40: Consumer | G40: Retail Partner | H40: James Whitfield | I40: 1 | J40: 186.81 | K40: 0.0969 | L40: =I40*J40*(1-K40) -> 168.70811 | M40: =ROUND(L40*0.2354,2) -> 39.71 | N40: =L40-M40 -> 128.99811
A41: ORD-2025-00040 | B41: 45676 | C41: West | D41: Accessories | E41: Wireless Headset | F41: Consumer | G41: Direct Sales | H41: Rachel Adams | I41: 2 | J41: 93.18 | K41: 0.0464 | L41: =I41*J41*(1-K41) -> 177.7129 | M41: =ROUND(L41*0.5952,2) -> 105.77 | N41: =L41-M41 -> 71.942896
A42: ORD-2025-00041 | B42: 45677 | C42: Southeast | D42: Electronics | E42: 27-inch 4K Monitor | F42: SMB | G42: Online | H42: Online Store - Southeast | I42: 9 | J42: 460.87 | K42: 0.0614 | L42: =I42*J42*(1-K42) -> 3893.1532 | M42: =ROUND(L42*0.7338,2) -> 2856.8 | N42: =L42-M42 -> 1036.3532
A43: ORD-2025-00042 | B43: 45677 | C43: Northeast | D43: Accessories | E43: Wireless Headset | F43: SMB | G43: Retail Partner | H43: Emily Carter | I43: 4 | J43: 96.63 | K43: 0.0941 | L43: =I43*J43*(1-K43) -> 350.14847 | M43: =ROUND(L43*0.5845,2) -> 204.66 | N43: =L43-M43 -> 145.48847
A44: ORD-2025-00043 | B44: 45677 | C44: Midwest | D44: Office Equipment | E44: All-in-One Printer | F44: Enterprise | G44: Direct Sales | H44: Robert Chen | I44: 35 | J44: 197.54 | K44: 0.1545 | L44: =I44*J44*(1-K44) -> 5845.7024 | M44: =ROUND(L44*0.6489,2) -> 3793.28 | N44: =L44-M44 -> 2052.4224
A45: ORD-2025-00044 | B45: 45677 | C45: West | D45: Office Equipment | E45: Paper Shredder | F45: SMB | G45: Online | H45: Online Store - West | I45: 7 | J45: 126.16 | K45: 0.0605 | L45: =I45*J45*(1-K45) -> 829.69124 | M45: =ROUND(L45*0.6115,2) -> 507.36 | N45: =L45-M45 -> 322.33124
A46: ORD-2025-00045 | B46: 45678 | C46: Southeast | D46: Office Equipment | E46: Standing Desk | F46: Consumer | G46: Retail Partner | H46: James Whitfield | I46: 3 | J46: 384.81 | K46: 0.0318 | L46: =I46*J46*(1-K46) -> 1117.7191 | M46: =ROUND(L46*0.6317,2) -> 706.06 | N46: =L46-M46 -> 411.65913
A47: ORD-2025-00046 | B47: 45678 | C47: Southeast | D47: Software | E47: Antivirus Security License | F47: SMB | G47: Online | H47: Online Store - Southeast | I47: 4 | J47: 59.83 | K47: 0.0372 | L47: =I47*J47*(1-K47) -> 230.4173 | M47: =ROUND(L47*0.2152,2) -> 49.59 | N47: =L47-M47 -> 180.8273
A48: ORD-2025-00047 | B48: 45679 | C48: Northeast | D48: Office Equipment | E48: Paper Shredder | F48: SMB | G48: Retail Partner | H48: Daniel Brooks | I48: 5 | J48: 129.94 | K48: 0.0731 | L48: =I48*J48*(1-K48) -> 602.20693 | M48: =ROUND(L48*0.6644,2) -> 400.11 | N48: =L48-M48 -> 202.09693
A49: ORD-2025-00048 | B49: 45679 | C49: West | D49: Electronics | E49: Business Desktop Tower | F49: SMB | G49: Retail Partner | H49: Sophia Martinez | I49: 8 | J49: 853.8 | K49: 0.0667 | L49: =I49*J49*(1-K49) -> 6374.8123 | M49: =ROUND(L49*0.7203,2) -> 4591.78 | N49: =L49-M49 -> 1783.0323
A50: ORD-2025-00049 | B50: 45680 | C50: West | D50: Office Equipment | E50: Paper Shredder | F50: Enterprise | G50: Direct Sales | H50: Rachel Adams | I50: 17 | J50: 125.71 | K50: 0.2032 | L50: =I50*J50*(1-K50) -> 1702.8174 | M50: =ROUND(L50*0.6319,2) -> 1076.01 | N50: =L50-M50 -> 626.80738
A51: ORD-2025-00050 | B51: 45681 | C51: West | D51: Electronics | E51: Ultrabook Air 13 | F51: Enterprise | G51: Direct Sales | H51: Rachel Adams | I51: 39 | J51: 1087.94 | K51: 0.1535 | L51: =I51*J51*(1-K51) -> 35916.707 | M51: =ROUND(L51*0.6846,2) -> 24588.58 | N51: =L51-M51 -> 11328.127
A52: ORD-2025-00051 | B52: 45681 | C52: Southeast | D52: Software | E52: Cloud Backup Subscription | F52: Enterprise | G52: Direct Sales | H52: Maria Gonzalez | I52: 26 | J52: 75.62 | K52: 0.1783 | L52: =I52*J52*(1-K52) -> 1615.5608 | M52: =ROUND(L52*0.2464,2) -> 398.07 | N52: =L52-M52 -> 1217.4908
A53: ORD-2025-00052 | B53: 45682 | C53: Northeast | D53: Office Equipment | E53: Laser Printer | F53: Enterprise | G53: Online | H53: Online Store - Northeast | I53: 35 | J53: 250.21 | K53: 0.0821 | L53: =I53*J53*(1-K53) -> 8038.3716 | M53: =ROUND(L53*0.6667,2) -> 5359.18 | N53: =L53-M53 -> 2679.1916
A54: ORD-2025-00053 | B54: 45682 | C54: Midwest | D54: Accessories | E54: Wireless Mouse | F54: Consumer | G54: Retail Partner | H54: Robert Chen | I54: 3 | J54: 38.96 | K54: 0.0579 | L54: =I54*J54*(1-K54) -> 110.11265 | M54: =ROUND(L54*0.5627,2) -> 61.96 | N54: =L54-M54 -> 48.152648
A55: ORD-2025-00054 | B55: 45682 | C55: Northeast | D55: Office Equipment | E55: All-in-One Printer | F55: Consumer | G55: Online | H55: Online Store - Northeast | I55: 1 | J55: 198.26 | K55: 0.0238 | L55: =I55*J55*(1-K55) -> 193.54141 | M55: =ROUND(L55*0.6626,2) -> 128.24 | N55: =L55-M55 -> 65.301412
A56: ORD-2025-00055 | B56: 45683 | C56: West | D56: Accessories | E56: USB-C Docking Station | F56: Consumer | G56: Retail Partner | H56: Kevin O'Brien | I56: 3 | J56: 149.34 | K56: 0.0477 | L56: =I56*J56*(1-K56) -> 426.64945 | M56: =ROUND(L56*0.5659,2) -> 241.44 | N56: =L56-M56 -> 185.20945
A57: ORD-2025-00056 | B57: 45683 | C57: Northeast | D57: Office Equipment | E57: Ergonomic Office Chair | F57: SMB | G57: Retail Partner | H57: Daniel Brooks | I57: 3 | J57: 321.15 | K57: 0.1088 | L57: =I57*J57*(1-K57) -> 858.62664 | M57: =ROUND(L57*0.6549,2) -> 562.31 | N57: =L57-M57 -> 296.31664
A58: ORD-2025-00057 | B58: 45685 | C58: Northeast | D58: Office Equipment | E58: Standing Desk | F58: Consumer | G58: Online | H58: Online Store - Northeast | I58: 1 | J58: 410.64 | K58: 0.0415 | L58: =I58*J58*(1-K58) -> 393.59844 | M58: =ROUND(L58*0.6586,2) -> 259.22 | N58: =L58-M58 -> 134.37844
A59: ORD-2025-00058 | B59: 45685 | C59: Midwest | D59: Accessories | E59: Laptop Sleeve 14-inch | F59: Enterprise | G59: Direct Sales | H59: Robert Chen | I59: 22 | J59: 27.9 | K59: 0.2328 | L59: =I59*J59*(1-K59) -> 470.90736 | M59: =ROUND(L59*0.5733,2) -> 269.97 | N59: =L59-M59 -> 200.93736
A60: ORD-2025-00059 | B60: 45685 | C60: Midwest | D60: Electronics | E60: Tablet Pro 11 | F60: SMB | G60: Direct Sales | H60: Robert Chen | I60: 6 | J60: 666.73 | K60: 0.1092 | L60: =I60*J60*(1-K60) -> 3563.5385 | M60: =ROUND(L60*0.6928,2) -> 2468.82 | N60: =L60-M60 -> 1094.7185
A61: ORD-2025-00060 | B61: 45686 | C61: West | D61: Accessories | E61: Mechanical Keyboard | F61: Consumer | G61: Online | H61: Online Store - West | I61: 2 | J61: 91.15 | K61: 0.049 | L61: =I61*J61*(1-K61) -> 173.3673 | M61: =ROUND(L61*0.5986,2) -> 103.78 | N61: =L61-M61 -> 69.5873
A62: ORD-2025-00061 | B62: 45686 | C62: Southeast | D62: Electronics | E62: 27-inch 4K Monitor | F62: Consumer | G62: Online | H62: Online Store - Southeast | I62: 1 | J62: 456.82 | K62: 0.0511 | L62: =I62*J62*(1-K62) -> 433.4765 | M62: =ROUND(L62*0.7181,2) -> 311.28 | N62: =L62-M62 -> 122.1965
A63: ORD-2025-00062 | B63: 45686 | C63: West | D63: Electronics | E63: Laptop Pro 14 | F63: Consumer | G63: Retail Partner | H63: Sophia Martinez | I63: 3 | J63: 1278.87 | K63: 0.0612 | L63: =I63*J63*(1-K63) -> 3601.8095 | M63: =ROUND(L63*0.7242,2) -> 2608.43 | N63: =L63-M63 -> 993.37947
A64: ORD-2025-00063 | B64: 45687 | C64: Southeast | D64: Accessories | E64: USB-C Docking Station | F64: Consumer | G64: Online | H64: Online Store - Southeast | I64: 1 | J64: 158.21 | K64: 0.0571 | L64: =I64*J64*(1-K64) -> 149.17621 | M64: =ROUND(L64*0.5682,2) -> 84.76 | N64: =L64-M64 -> 64.416209
A65: ORD-2025-00064 | B65: 45687 | C65: West | D65: Office Equipment | E65: Standing Desk | F65: Enterprise | G65: Direct Sales | H65: Sophia Martinez | I65: 23 | J65: 396.24 | K65: 0.151 | L65: =I65*J65*(1-K65) -> 7737.3785 | M65: =ROUND(L65*0.6436,2) -> 4979.78 | N65: =L65-M65 -> 2757.5985
A66: ORD-2025-00065 | B66: 45687 | C66: West | D66: Electronics | E66: Laptop Pro 14 | F66: SMB | G66: Direct Sales | H66: Sophia Martinez | I66: 6 | J66: 1232.48 | K66: 0.1298 | L66: =I66*J66*(1-K66) -> 6435.0246 | M66: =ROUND(L66*0.731,2) -> 4704 | N66: =L66-M66 -> 1731.0246
A67: ORD-2025-00066 | B67: 45688 | C67: Southeast | D67: Office Equipment | E67: Ergonomic Office Chair | F67: SMB | G67: Direct Sales | H67: James Whitfield | I67: 8 | J67: 325.1 | K67: 0.1697 | L67: =I67*J67*(1-K67) -> 2159.4442 | M67: =ROUND(L67*0.6538,2) -> 1411.84 | N67: =L67-M67 -> 747.60424
A68: ORD-2025-00067 | B68: 45688 | C68: Midwest | D68: Electronics | E68: Business Desktop Tower | F68: Consumer | G68: Direct Sales | H68: Laura Kim | I68: 2 | J68: 876.54 | K68: 0.0105 | L68: =I68*J68*(1-K68) -> 1734.6727 | M68: =ROUND(L68*0.6869,2) -> 1191.55 | N68: =L68-M68 -> 543.12266
A69: ORD-2025-00068 | B69: 45689 | C69: West | D69: Electronics | E69: Ultrabook Air 13 | F69: Enterprise | G69: Online | H69: Online Store - West | I69: 9 | J69: 1142.92 | K69: 0.0821 | L69: =I69*J69*(1-K69) -> 9441.7764 | M69: =ROUND(L69*0.6962,2) -> 6573.36 | N69: =L69-M69 -> 2868.4164
A70: ORD-2025-00069 | B70: 45690 | C70: Midwest | D70: Electronics | E70: Business Desktop Tower | F70: SMB | G70: Direct Sales | H70: Laura Kim | I70: 7 | J70: 858.57 | K70: 0.1207 | L70: =I70*J70*(1-K70) -> 5284.5842 | M70: =ROUND(L70*0.7181,2) -> 3794.86 | N70: =L70-M70 -> 1489.7242
A71: ORD-2025-00070 | B71: 45690 | C71: West | D71: Accessories | E71: Mechanical Keyboard | F71: SMB | G71: Online | H71: Online Store - West | I71: 4 | J71: 90.33 | K71: 0.0586 | L71: =I71*J71*(1-K71) -> 340.14665 | M71: =ROUND(L71*0.5973,2) -> 203.17 | N71: =L71-M71 -> 136.97665
A72: ORD-2025-00071 | B72: 45691 | C72: Southeast | D72: Office Equipment | E72: Standing Desk | F72: Consumer | G72: Online | H72: Online Store - Southeast | I72: 3 | J72: 394.93 | K72: 0.065 | L72: =I72*J72*(1-K72) -> 1107.7786 | M72: =ROUND(L72*0.6136,2) -> 679.73 | N72: =L72-M72 -> 428.04865
A73: ORD-2025-00072 | B73: 45691 | C73: Midwest | D73: Office Equipment | E73: Standing Desk | F73: Enterprise | G73: Direct Sales | H73: Robert Chen | I73: 17 | J73: 400.05 | K73: 0.1466 | L73: =I73*J73*(1-K73) -> 5803.8454 | M73: =ROUND(L73*0.6266,2) -> 3636.69 | N73: =L73-M73 -> 2167.1554
A74: ORD-2025-00073 | B74: 45691 | C74: Midwest | D74: Accessories | E74: Wireless Headset | F74: SMB | G74: Online | H74: Online Store - Midwest | I74: 7 | J74: 98.52 | K74: 0.0523 | L74: =I74*J74*(1-K74) -> 653.57183 | M74: =ROUND(L74*0.5682,2) -> 371.36 | N74: =L74-M74 -> 282.21183
A75: ORD-2025-00074 | B75: 45692 | C75: Midwest | D75: Software | E75: Project Management License | F75: SMB | G75: Retail Partner | H75: Laura Kim | I75: 8 | J75: 186.98 | K75: 0.0828 | L75: =I75*J75*(1-K75) -> 1371.9844 | M75: =ROUND(L75*0.2115,2) -> 290.17 | N75: =L75-M75 -> 1081.8144
A76: ORD-2025-00075 | B76: 45692 | C76: Northeast | D76: Electronics | E76: Business Desktop Tower | F76: Enterprise | G76: Direct Sales | H76: Emily Carter | I76: 17 | J76: 902.95 | K76: 0.2369 | L76: =I76*J76*(1-K76) -> 11713.699 | M76: =ROUND(L76*0.6851,2) -> 8025.06 | N76: =L76-M76 -> 3688.6395
A77: ORD-2025-00076 | B77: 45692 | C77: Southeast | D77: Software | E77: Antivirus Security License | F77: Enterprise | G77: Direct Sales | H77: James Whitfield | I77: 19 | J77: 59.97 | K77: 0.1667 | L77: =I77*J77*(1-K77) -> 949.48702 | M77: =ROUND(L77*0.2617,2) -> 248.48 | N77: =L77-M77 -> 701.00702
A78: ORD-2025-00077 | B78: 45692 | C78: West | D78: Accessories | E78: Laptop Sleeve 14-inch | F78: SMB | G78: Direct Sales | H78: Rachel Adams | I78: 3 | J78: 28.19 | K78: 0.1297 | L78: =I78*J78*(1-K78) -> 73.601271 | M78: =ROUND(L78*0.5573,2) -> 41.02 | N78: =L78-M78 -> 32.581271
A79: ORD-2025-00078 | B79: 45692 | C79: Southeast | D79: Accessories | E79: Laptop Sleeve 14-inch | F79: Enterprise | G79: Direct Sales | H79: James Whitfield | I79: 31 | J79: 28.95 | K79: 0.1713 | L79: =I79*J79*(1-K79) -> 743.71681 | M79: =ROUND(L79*0.5677,2) -> 422.21 | N79: =L79-M79 -> 321.50681
A80: ORD-2025-00079 | B80: 45693 | C80: West | D80: Office Equipment | E80: All-in-One Printer | F80: Enterprise | G80: Direct Sales | H80: Sophia Martinez | I80: 9 | J80: 189.28 | K80: 0.2135 | L80: =I80*J80*(1-K80) -> 1339.8185 | M80: =ROUND(L80*0.6573,2) -> 880.66 | N80: =L80-M80 -> 459.15848
A81: ORD-2025-00080 | B81: 45693 | C81: West | D81: Office Equipment | E81: Paper Shredder | F81: Consumer | G81: Online | H81: Online Store - West | I81: 1 | J81: 126.26 | K81: 0.041 | L81: =I81*J81*(1-K81) -> 121.08334 | M81: =ROUND(L81*0.6333,2) -> 76.68 | N81: =L81-M81 -> 44.40334
A82: ORD-2025-00081 | B82: 45694 | C82: Northeast | D82: Accessories | E82: Mechanical Keyboard | F82: Enterprise | G82: Retail Partner | H82: Emily Carter | I82: 30 | J82: 85.47 | K82: 0.1515 | L82: =I82*J82*(1-K82) -> 2175.6388 | M82: =ROUND(L82*0.5819,2) -> 1266 | N82: =L82-M82 -> 909.63885
A83: ORD-2025-00082 | B83: 45696 | C83: Midwest | D83: Electronics | E83: 27-inch 4K Monitor | F83: SMB | G83: Online | H83: Online Store - Midwest | I83: 6 | J83: 458.9 | K83: 0.0764 | L83: =I83*J83*(1-K83) -> 2543.0402 | M83: =ROUND(L83*0.7345,2) -> 1867.86 | N83: =L83-M83 -> 675.18024
A84: ORD-2025-00083 | B84: 45696 | C84: Midwest | D84: Accessories | E84: Wireless Headset | F84: Consumer | G84: Retail Partner | H84: Laura Kim | I84: 3 | J84: 98.08 | K84: 0.0581 | L84: =I84*J84*(1-K84) -> 277.14466 | M84: =ROUND(L84*0.5582,2) -> 154.7 | N84: =L84-M84 -> 122.44466
A85: ORD-2025-00084 | B85: 45697 | C85: West | D85: Electronics | E85: Laptop Pro 14 | F85: Enterprise | G85: Direct Sales | H85: Kevin O'Brien | I85: 29 | J85: 1304 | K85: 0.1781 | L85: =I85*J85*(1-K85) -> 31080.97 | M85: =ROUND(L85*0.6845,2) -> 21274.92 | N85: =L85-M85 -> 9806.0504
A86: ORD-2025-00085 | B86: 45697 | C86: Southeast | D86: Electronics | E86: Ultrabook Air 13 | F86: SMB | G86: Online | H86: Online Store - Southeast | I86: 5 | J86: 1071.88 | K86: 0.0513 | L86: =I86*J86*(1-K86) -> 5084.4628 | M86: =ROUND(L86*0.6966,2) -> 3541.84 | N86: =L86-M86 -> 1542.6228
A87: ORD-2025-00086 | B87: 45697 | C87: West | D87: Software | E87: Cloud Backup Subscription | F87: SMB | G87: Online | H87: Online Store - West | I87: 10 | J87: 81.1 | K87: 0.0521 | L87: =I87*J87*(1-K87) -> 768.7469 | M87: =ROUND(L87*0.2565,2) -> 197.18 | N87: =L87-M87 -> 571.5669
A88: ORD-2025-00087 | B88: 45698 | C88: Southeast | D88: Software | E88: Project Management License | F88: Enterprise | G88: Direct Sales | H88: Maria Gonzalez | I88: 14 | J88: 202 | K88: 0.1393 | L88: =I88*J88*(1-K88) -> 2434.0596 | M88: =ROUND(L88*0.2227,2) -> 542.07 | N88: =L88-M88 -> 1891.9896
A89: ORD-2025-00088 | B89: 45698 | C89: West | D89: Software | E89: Cloud Backup Subscription | F89: SMB | G89: Retail Partner | H89: Sophia Martinez | I89: 4 | J89: 75.49 | K89: 0.0832 | L89: =I89*J89*(1-K89) -> 276.83693 | M89: =ROUND(L89*0.2682,2) -> 74.25 | N89: =L89-M89 -> 202.58693
A90: ORD-2025-00089 | B90: 45699 | C90: Southeast | D90: Electronics | E90: Laptop Pro 14 | F90: Consumer | G90: Online | H90: Online Store - Southeast | I90: 3 | J90: 1291.75 | K90: 0.0011 | L90: =I90*J90*(1-K90) -> 3870.9872 | M90: =ROUND(L90*0.6869,2) -> 2658.98 | N90: =L90-M90 -> 1212.0072
A91: ORD-2025-00090 | B91: 45699 | C91: Southeast | D91: Accessories | E91: Wireless Headset | F91: Consumer | G91: Online | H91: Online Store - Southeast | I91: 3 | J91: 99.76 | K91: 0.0488 | L91: =I91*J91*(1-K91) -> 284.67514 | M91: =ROUND(L91*0.5593,2) -> 159.22 | N91: =L91-M91 -> 125.45514
A92: ORD-2025-00091 | B92: 45699 | C92: Northeast | D92: Accessories | E92: Wireless Mouse | F92: SMB | G92: Online | H92: Online Store - Northeast | I92: 8 | J92: 39.93 | K92: 0.0687 | L92: =I92*J92*(1-K92) -> 297.49447 | M92: =ROUND(L92*0.6028,2) -> 179.33 | N92: =L92-M92 -> 118.16447
A93: ORD-2025-00092 | B93: 45700 | C93: West | D93: Software | E93: Cloud Backup Subscription | F93: SMB | G93: Direct Sales | H93: Rachel Adams | I93: 10 | J93: 79.56 | K93: 0.0916 | L93: =I93*J93*(1-K93) -> 722.72304 | M93: =ROUND(L93*0.2331,2) -> 168.47 | N93: =L93-M93 -> 554.25304
A94: ORD-2025-00093 | B94: 45700 | C94: West | D94: Electronics | E94: Ultrabook Air 13 | F94: SMB | G94: Retail Partner | H94: Kevin O'Brien | I94: 5 | J94: 1098.9 | K94: 0.128 | L94: =I94*J94*(1-K94) -> 4791.204 | M94: =ROUND(L94*0.73,2) -> 3497.58 | N94: =L94-M94 -> 1293.624
A95: ORD-2025-00094 | B95: 45700 | C95: Midwest | D95: Electronics | E95: 27-inch 4K Monitor | F95: Consumer | G95: Online | H95: Online Store - Midwest | I95: 3 | J95: 455 | K95: 0.0573 | L95: =I95*J95*(1-K95) -> 1286.7855 | M95: =ROUND(L95*0.7037,2) -> 905.51 | N95: =L95-M95 -> 381.2755
A96: ORD-2025-00095 | B96: 45701 | C96: Southeast | D96: Software | E96: Antivirus Security License | F96: Consumer | G96: Online | H96: Online Store - Southeast | I96: 2 | J96: 58.41 | K96: 0.0653 | L96: =I96*J96*(1-K96) -> 109.19165 | M96: =ROUND(L96*0.2654,2) -> 28.98 | N96: =L96-M96 -> 80.211654
A97: ORD-2025-00096 | B97: 45701 | C97: Northeast | D97: Office Equipment | E97: All-in-One Printer | F97: Enterprise | G97: Direct Sales | H97: Daniel Brooks | I97: 11 | J97: 190.15 | K97: 0.2308 | L97: =I97*J97*(1-K97) -> 1608.8972 | M97: =ROUND(L97*0.6554,2) -> 1054.47 | N97: =L97-M97 -> 554.42718
A98: ORD-2025-00097 | B98: 45701 | C98: Southeast | D98: Accessories | E98: Wireless Mouse | F98: Enterprise | G98: Direct Sales | H98: Maria Gonzalez | I98: 10 | J98: 39.41 | K98: 0.1893 | L98: =I98*J98*(1-K98) -> 319.49687 | M98: =ROUND(L98*0.5862,2) -> 187.29 | N98: =L98-M98 -> 132.20687
A99: ORD-2025-00098 | B99: 45702 | C99: Southeast | D99: Accessories | E99: Laptop Sleeve 14-inch | F99: SMB | G99: Online | H99: Online Store - Southeast | I99: 7 | J99: 29.52 | K99: 0.0752 | L99: =I99*J99*(1-K99) -> 191.10067 | M99: =ROUND(L99*0.5848,2) -> 111.76 | N99: =L99-M99 -> 79.340672
A100: ORD-2025-00099 | B100: 45703 | C100: West | D100: Office Equipment | E100: All-in-One Printer | F100: Consumer | G100: Retail Partner | H100: Rachel Adams | I100: 1 | J100: 198.65 | K100: 0.0835 | L100: =I100*J100*(1-K100) -> 182.06273 | M100: =ROUND(L100*0.6574,2) -> 119.69 | N100: =L100-M100 -> 62.372725
...

Sheet Products
A1: Product | B1: Category | C1: Standard Price
A2: Laptop Pro 14 | B2: Electronics | C2: 1299
A3: Ultrabook Air 13 | B3: Electronics | C3: 1099
A4: Business Desktop Tower | B4: Electronics | C4: 899
A5: 27-inch 4K Monitor | B5: Electronics | C5: 449
A6: Tablet Pro 11 | B6: Electronics | C6: 699
A7: Wireless Mouse | B7: Accessories | C7: 39
A8: Mechanical Keyboard | B8: Accessories | C8: 89
A9: USB-C Docking Station | B9: Accessories | C9: 159
A10: Laptop Sleeve 14-inch | B10: Accessories | C10: 29
A11: Wireless Headset | B11: Accessories | C11: 99
A12: Laser Printer | B12: Office Equipment | C12: 249
A13: All-in-One Printer | B13: Office Equipment | C13: 199
... A21: Accounting Software License | B21: Software | C21: 249

Sheet Monthly_Targets
A1: Month | B1: Sales | C1: Sales Target | E1: Variance vs Target %
A2: January | B2: =SUMPRODUCT((YEAR(Sales_Data!$B$2:$B$1201)=2025)*(MONTH(Sales_Data!$B$2:$B$1201)=ROW()-1)*Sales_Data!$L$2:$L$1201) -> 249219.22 | C2: 239300 | E2: =(B2-C2)/C2 -> 0.04145099
A3: February | B3: =SUMPRODUCT((YEAR(Sales_Data!$B$2:$B$1201)=2025)*(MONTH(Sales_Data!$B$2:$B$1201)=ROW()-1)*Sales_Data!$L$2:$L$1201) -> 173602.68 | C3: 158300 | E3: =(B3-C3)/C3 -> 0.09666884
A4: March | B4: =SUMPRODUCT((YEAR(Sales_Data!$B$2:$B$1201)=2025)*(MONTH(Sales_Data!$B$2:$B$1201)=ROW()-1)*Sales_Data!$L$2:$L$1201) -> 229353.72 | C4: 234700 | E4: =(B4-C4)/C4 -> -0.022779218
A5: April | B5: =SUMPRODUCT((YEAR(Sales_Data!$B$2:$B$1201)=2025)*(MONTH(Sales_Data!$B$2:$B$1201)=ROW()-1)*Sales_Data!$L$2:$L$1201) -> 229100.73 | C5: 208000 | E5: =(B5-C5)/C5 -> 0.10144581
A6: May | B6: =SUMPRODUCT((YEAR(Sales_Data!$B$2:$B$1201)=2025)*(MONTH(Sales_Data!$B$2:$B$1201)=ROW()-1)*Sales_Data!$L$2:$L$1201) -> 242858.01 | C6: 239700 | E6: =(B6-C6)/C6 -> 0.013174835
A7: June | B7: =SUMPRODUCT((YEAR(Sales_Data!$B$2:$B$1201)=2025)*(MONTH(Sales_Data!$B$2:$B$1201)=ROW()-1)*Sales_Data!$L$2:$L$1201) -> 205923.87 | C7: 193900 | E7: =(B7-C7)/C7 -> 0.062010669
A8: July | B8: =SUMPRODUCT((YEAR(Sales_Data!$B$2:$B$1201)=2025)*(MONTH(Sales_Data!$B$2:$B$1201)=ROW()-1)*Sales_Data!$L$2:$L$1201) -> 219914.48 | C8: 194900 | E8: =(B8-C8)/C8 -> 0.12834521
A9: August | B9: =SUMPRODUCT((YEAR(Sales_Data!$B$2:$B$1201)=2025)*(MONTH(Sales_Data!$B$2:$B$1201)=ROW()-1)*Sales_Data!$L$2:$L$1201) -> 287238.09 | C9: 284300 | E9: =(B9-C9)/C9 -> 0.010334484
A10: September | B10: =SUMPRODUCT((YEAR(Sales_Data!$B$2:$B$1201)=2025)*(MONTH(Sales_Data!$B$2:$B$1201)=ROW()-1)*Sales_Data!$L$2:$L$1201) -> 304839.51 | C10: 267400 | E10: =(B10-C10)/C10 -> 0.14001313
A11: October | B11: =SUMPRODUCT((YEAR(Sales_Data!$B$2:$B$1201)=2025)*(MONTH(Sales_Data!$B$2:$B$1201)=ROW()-1)*Sales_Data!$L$2:$L$1201) -> 224738.54 | C11: 219900 | E11: =(B11-C11)/C11 -> 0.022003362
A12: November | B12: =SUMPRODUCT((YEAR(Sales_Data!$B$2:$B$1201)=2025)*(MONTH(Sales_Data!$B$2:$B$1201)=ROW()-1)*Sales_Data!$L$2:$L$1201) -> 343748.28 | C12: 300600 | E12: =(B12-C12)/C12 -> 0.1435405
A13: December | B13: =SUMPRODUCT((YEAR(Sales_Data!$B$2:$B$1201)=2025)*(MONTH(Sales_Data!$B$2:$B$1201)=ROW()-1)*Sales_Data!$L$2:$L$1201) -> 355963.59 | C13: 321700 | E13: =(B13-C13)/C13 -> 0.10650788
